tkdev5/__init__.py
tkdev5/acrylic/__init__.py
tkdev5/acrylic/acrylic.dll
tkdev5/acrylic/acrylic.py
tkdev5/acrylic/c_structures.py
tkdev5/method_sets.py
tkdev5/old/__init__.py
tkdev5/old/devicon.py
tkdev5/old/devmanage.py
tkdev5/old/devstack.py
tkdev5/toast.py
tkdev5/toast_advanced/__init__.py
tkdev5/toast_advanced/Microsoft.Toolkit.Uwp.Notifications.dll
tkdev5/toast_advanced/Microsoft.Toolkit.Uwp.Notifications.pdb
tkdev5/toast_advanced/Microsoft.Toolkit.Uwp.Notifications.xml
tkdev5/toast_advanced/test.cls
tkdev5/tray.py
tkdev5/ttree/__init__.py
tkdev5/wf.py
tkdev5/winforms.py
tkdev5-0.1.0.dist-info/METADATA
tkdev5-0.1.0.dist-info/WHEEL
tkdev5-0.1.0.dist-info/RECORD
